arcaflow_lib_kubernetes/__init__.py
arcaflow_lib_kubernetes/convert.py
arcaflow_lib_kubernetes/model.py
arcaflow_lib_kubernetes/test_convert.py
arcaflow_lib_kubernetes-0.2.1.dist-info/LICENSE
arcaflow_lib_kubernetes-0.2.1.dist-info/METADATA
arcaflow_lib_kubernetes-0.2.1.dist-info/WHEEL
arcaflow_lib_kubernetes-0.2.1.dist-info/RECORD
