Metadata-Version: 2.1
Name: arcaflow-lib-kubernetes
Version: 0.2.1
Summary: Kubernetes connection handling library for Arcaflow
License: Apache-2.0
Author: Arcalot Contributors
Requires-Python: >=3.9,<4.0
Classifier: License :: OSI Approved :: Apache Software License
Classifier: Programming Language :: Python :: 3
Classifier: Programming Language :: Python :: 3.9
Classifier: Programming Language :: Python :: 3.10
Classifier: Programming Language :: Python :: 3.11
Requires-Dist: PyYAML (>=5.4)
Requires-Dist: arcaflow-plugin-sdk (>=0.14.0,<0.15.0)
Requires-Dist: coverage (>=7.2.1,<8.0.0)
Requires-Dist: html2text (>=2024.0.0,<2025.0.0)
Requires-Dist: kubernetes (>=25.3.0)
Requires-Dist: pylint (>=3.0.0,<4.0.0)
Requires-Dist: sphinxcontrib-apidoc (>=0.5.0,<0.6.0)
